{
  "notifications": [
    {
      "id": "1773556465900",
      "timestamp": "2026-03-15T06:34:25.900Z",
      "status": "success",
      "riskLevel": "risky",
      "recipient": "unknown0506hacker@gmail.com",
      "summary": "HR 130, BP 120, SpO2 99, Glucose 82",
      "messagePreview": "Hi Tej,\n\nHello! Let's review your current health data.\n\nYour Heart Rate is significantly elevated at...",
      "messageId": "<1bff6190-3a70-7fb8-4bc3-b32b585ff5c2@gmail.com>",
      "response": "250 2.0.0 OK  1773556463 d9443c01a7336-2b04f40f515sm14973755ad.74 - gsmtp"
    },
    {
      "id": "1773556461687",
      "timestamp": "2026-03-15T06:34:21.687Z",
      "status": "success",
      "riskLevel": "risky",
      "recipient": "asha@safemom.com",
      "summary": "HR 130, BP 120, SpO2 99, Glucose 82",
      "messagePreview": "Hi Rani Devi and your patient Tanu,\n\nHello! Let's review your current health data.\n\nYour Heart Rate ...",
      "messageId": "<755f7c15-7264-5022-fac5-964fd5a62690@gmail.com>",
      "response": "250 2.0.0 OK  1773556459 41be03b00d2f7-c7402214e1csm683419a12.33 - gsmtp"
    },
    {
      "id": "1773556457448",
      "timestamp": "2026-03-15T06:34:17.448Z",
      "status": "success",
      "riskLevel": "risky",
      "recipient": "eswardhavala1@gmail.com",
      "summary": "HR 130, BP 120, SpO2 99, Glucose 82",
      "messagePreview": "Hi Tej and your patient Tanu,\n\nHello! Let's review your current health data.\n\nYour Heart Rate is sig...",
      "messageId": "<777c2e71-e6bb-d08d-99a5-ae3a0a9b34ae@gmail.com>",
      "response": "250 2.0.0 OK  1773556454 d9443c01a7336-2aece62c4f9sm72560095ad.38 - gsmtp"
    },
    {
      "id": "1773556453279",
      "timestamp": "2026-03-15T06:34:13.279Z",
      "status": "success",
      "riskLevel": "risky",
      "recipient": "tanujach979@gmail.com",
      "summary": "HR 130, BP 120, SpO2 99, Glucose 82",
      "messagePreview": "Hi Tanu,\n\nHello! Let's review your current health data.\n\nYour Heart Rate is significantly elevated a...",
      "messageId": "<2cf7cbc9-bfee-6b03-9038-a34a8f9c79aa@gmail.com>",
      "response": "250 2.0.0 OK  1773556450 98e67ed59e1d1-35a03005f7fsm12875812a91.15 - gsmtp"
    },
    {
      "id": "1773213827706",
      "timestamp": "2026-03-11T07:23:47.706Z",
      "status": "success",
      "riskLevel": "risky",
      "recipient": "eswardhavala1@gmail.com",
      "summary": "HR 120, BP 140, SpO2 99, Glucose 89",
      "messagePreview": "Based on your current vital signs and reported symptoms, your overall health risk is classified as *...",
      "messageId": "<ecde716b-34ec-01ba-059a-972496711ac3@gmail.com>",
      "response": "250 2.0.0 OK  1773213827 d9443c01a7336-2aeae2557casm13746095ad.35 - gsmtp"
    },
    {
      "id": "1773213823516",
      "timestamp": "2026-03-11T07:23:43.516Z",
      "status": "success",
      "riskLevel": "risky",
      "recipient": "tanujach979@gmail.com",
      "summary": "HR 120, BP 140, SpO2 99, Glucose 89",
      "messagePreview": "Based on your current vital signs and reported symptoms, your overall health risk is classified as *...",
      "messageId": "<676b25a9-72c9-a1de-7f29-26d944e1b15c@gmail.com>",
      "response": "250 2.0.0 OK  1773213823 d9443c01a7336-2aeae34de2dsm14190745ad.59 - gsmtp"
    },
    {
      "id": "1773212612579",
      "timestamp": "2026-03-11T07:03:32.579Z",
      "status": "success",
      "riskLevel": "high",
      "recipient": "eswardhavala1@gamil.com",
      "summary": "HR 79, BP 120, SpO2 99, Glucose 150",
      "messagePreview": "Your current vital signs and symptoms show some areas that need attention. While most of your vitals...",
      "messageId": "<2e6f5725-559c-169c-428c-fba483dd3cf5@gmail.com>",
      "response": "250 2.0.0 OK  1773212612 d9443c01a7336-2aeae222ec3sm16284755ad.1 - gsmtp"
    },
    {
      "id": "1773212609035",
      "timestamp": "2026-03-11T07:03:29.035Z",
      "status": "success",
      "riskLevel": "high",
      "recipient": "tanujach979@gmail.com",
      "summary": "HR 79, BP 120, SpO2 99, Glucose 150",
      "messagePreview": "Your current vital signs and symptoms show some areas that need attention. While most of your vitals...",
      "messageId": "<caa7706e-0b78-fc21-93cd-0227094da41f@gmail.com>",
      "response": "250 2.0.0 OK  1773212608 41be03b00d2f7-c73cde37ffesm1182073a12.0 - gsmtp"
    },
    {
      "id": "1773212335475",
      "timestamp": "2026-03-11T06:58:55.475Z",
      "status": "success",
      "riskLevel": "risky",
      "recipient": "eswardhavala1@gmail.com",
      "summary": "HR 79, BP 160, SpO2 99, Glucose 90",
      "messagePreview": "Your vital signs and symptoms indicate several areas that need immediate attention.\n\nYour **blood pr...",
      "messageId": "<2ddd3bfa-5e4d-304a-84ce-70a729f713ee@gmail.com>",
      "response": "250 2.0.0 OK  1773212335 d2e1a72fcca58-829f6df3b14sm1384825b3a.20 - gsmtp"
    },
    {
      "id": "1773207995384",
      "timestamp": "2026-03-11T05:46:35.384Z",
      "status": "success",
      "riskLevel": "high",
      "recipient": "eswardhavala1@gmail.com",
      "summary": "HR 120, BP 145, SpO2 92, Glucose 150",
      "messagePreview": "Test alert: High risk detected. Heart rate elevated, blood pressure high, oxygen saturation low....",
      "messageId": "<5fe54fbe-1613-f559-3c2a-0a6e01e18fce@gmail.com>",
      "response": "250 2.0.0 OK  1773207987 98e67ed59e1d1-35a00332df4sm568896a91.1 - gsmtp"
    },
    {
      "id": "1773153298808",
      "timestamp": "2026-03-10T14:34:58.808Z",
      "status": "success",
      "riskLevel": "high",
      "recipient": "eswardhavala1@gmail.com",
      "summary": "Chat assessment",
      "messagePreview": "I understand you've been diagnosed with preeclampsia. This is a condition that requires close medica...",
      "messageId": "<7a79327f-c6f0-e808-d684-aaa618dea9eb@gmail.com>",
      "response": "250 2.0.0 OK  1773153291 d9443c01a7336-2ae83f8c713sm151502455ad.66 - gsmtp"
    },
    {
      "id": "1773152026615",
      "timestamp": "2026-03-10T14:13:46.615Z",
      "status": "success",
      "riskLevel": "high",
      "recipient": "eswardhavala1@gmail.com",
      "summary": "Chat assessment",
      "messagePreview": "Experiencing swelling in your eyes, especially when combined with leg swelling, can be a concerning ...",
      "messageId": "<95dbeebb-ccf5-e90a-e9aa-181fafeb6f8d@gmail.com>",
      "response": "250 2.0.0 OK  1773152019 d9443c01a7336-2aeab727059sm3461005ad.17 - gsmtp"
    },
    {
      "id": "1773152001219",
      "timestamp": "2026-03-10T14:13:21.219Z",
      "status": "success",
      "riskLevel": "high",
      "recipient": "eswardhavala1@gmail.com",
      "summary": "Chat assessment",
      "messagePreview": "I understand you're experiencing heavy swelling in your legs. While some swelling can be normal duri...",
      "messageId": "<54f11bf2-95af-7da4-f924-eb302cc2900a@gmail.com>",
      "response": "250 2.0.0 OK  1773151993 d2e1a72fcca58-829aeea86b9sm15023200b3a.34 - gsmtp"
    },
    {
      "id": "1773150790711",
      "timestamp": "2026-03-10T13:53:10.711Z",
      "status": "success",
      "riskLevel": "high",
      "recipient": "eswardhavala1@gmail.com",
      "summary": "Chat assessment",
      "messagePreview": "I'm concerned to hear about heavy swelling in your legs. While some swelling can be common during pr...",
      "messageId": "<ad837bdf-5daf-b61f-c2f8-86e3c22b3ad7@gmail.com>",
      "response": "250 2.0.0 OK  1773150783 d9443c01a7336-2ae83fa81d5sm155105455ad.71 - gsmtp"
    },
    {
      "id": "1773149564497",
      "timestamp": "2026-03-10T13:32:44.497Z",
      "status": "success",
      "riskLevel": "high",
      "recipient": "eswardhavala1@gmail.com",
      "summary": "Chat assessment",
      "messagePreview": "I'm very concerned to hear about heavy bleeding in your wrist. This sounds like a medical emergency ...",
      "messageId": "<6616cbcc-f845-4e6b-46f5-b78fe45d1ec1@gmail.com>",
      "response": "250 2.0.0 OK  1773149557 d2e1a72fcca58-829a48a2258sm13646372b3a.46 - gsmtp"
    },
    {
      "id": "1773143959242",
      "timestamp": "2026-03-10T11:59:19.242Z",
      "status": "success",
      "riskLevel": "high",
      "recipient": "eswardhavala1@gmail.com",
      "summary": "HR 79, BP 150, SpO2 99, Glucose 120",
      "messagePreview": "Hello Tanu,\n\nBased on your current vital signs and reported symptoms, your overall risk level is cla...",
      "messageId": "<ba050205-0ca5-f498-cfae-e1cdec6d5de1@gmail.com>",
      "response": "250 2.0.0 OK  1773143951 d9443c01a7336-2ae83e57c1csm212415545ad.18 - gsmtp"
    },
    {
      "id": "1773142347528",
      "timestamp": "2026-03-10T11:32:27.528Z",
      "status": "success",
      "riskLevel": "risky",
      "recipient": "eswardhavala1@gmail.com",
      "summary": "HR 77, BP 120, SpO2 91, Glucose 124",
      "messagePreview": "Hello there! Thank you for sharing your vital signs and symptoms. Let's look at these together.\n\nYou...",
      "messageId": "<aee72948-baa9-64fe-e9e2-f7b62276701b@gmail.com>",
      "response": "250 2.0.0 OK  1773142339 d2e1a72fcca58-829a48b2c41sm13133017b3a.54 - gsmtp"
    },
    {
      "id": "1772952849163",
      "timestamp": "2026-03-08T06:54:09.163Z",
      "status": "success",
      "riskLevel": "high",
      "recipient": "eswardhavala1@gmail.com",
      "summary": "HR 80, BP 120, SpO2 99, Glucose 148",
      "messagePreview": "Hello Radha, thank you for sharing your information. Let's look at your current health status.\n\nBase...",
      "messageId": "<899fccb7-1684-8908-15ab-7ae8221a6ddf@gmail.com>",
      "response": "250 2.0.0 OK  1772952842 98e67ed59e1d1-359b2d3922dsm10142019a91.2 - gsmtp"
    },
    {
      "id": "1770461152932",
      "timestamp": "2026-02-07T10:45:52.932Z",
      "status": "success",
      "riskLevel": "risky",
      "recipient": "eswardhavala1@gmail.com",
      "summary": "HR 70, BP 180, SpO2 99, Glucose 150",
      "messagePreview": "Hello Radha,\n\nBased on your current vital signs and symptoms, your overall risk level is **Risky**.\n...",
      "messageId": "<9510f469-99d8-e813-e22e-08ec57eba0c6@gmail.com>",
      "response": "250 2.0.0 OK  1770461125 d9443c01a7336-2a952205e83sm72151345ad.81 - gsmtp"
    },
    {
      "id": "1770458725645",
      "timestamp": "2026-02-07T10:05:25.645Z",
      "status": "success",
      "riskLevel": "high",
      "recipient": "eswardhavala1@gmail.com",
      "summary": "HR 90, BP 120, SpO2 99, Glucose 163",
      "messagePreview": "Hello there! Thank you for sharing your vital signs and symptoms.\n\nBased on your current vitals and ...",
      "messageId": "<d993874b-5db6-8580-4408-95c2fe53e2a4@gmail.com>",
      "response": "250 2.0.0 OK  1770458698 98e67ed59e1d1-354b1f49186sm4683140a91.5 - gsmtp"
    },
    {
      "id": "1770446744429",
      "timestamp": "2026-02-07T06:45:44.429Z",
      "status": "success",
      "riskLevel": "risky",
      "recipient": "eswardhavala1@gmail.com",
      "summary": "HR 100, BP 150, SpO2 99, Glucose 80",
      "messagePreview": "Hello there. Let's look at your current health status.\n\nBased on your elevated Blood Pressure (150 m...",
      "messageId": "<2f9b58eb-ad14-bc17-3da7-fea1a901963c@gmail.com>",
      "response": "250 2.0.0 OK  1770446716 d9443c01a7336-2aad174a28bsm6579715ad.44 - gsmtp"
    },
    {
      "id": "1770446251277",
      "timestamp": "2026-02-07T06:37:31.277Z",
      "status": "success",
      "riskLevel": "risky",
      "recipient": "eswardhavala1@gmail.com",
      "summary": "HR 100, BP 189, SpO2 99, Glucose 220",
      "messagePreview": "Hello! Thank you for sharing your current vital signs and symptoms.\n\nYour Heart Rate, Stress Level, ...",
      "messageId": "<4b80ceb9-3998-cd37-71cc-778dbcd8ce5d@gmail.com>",
      "response": "250 2.0.0 OK  1770446223 41be03b00d2f7-c6de0128b6esm616611a12.26 - gsmtp"
    },
    {
      "id": "1770446097063",
      "timestamp": "2026-02-07T06:34:57.063Z",
      "status": "success",
      "riskLevel": "risky",
      "recipient": "eswardhavala1@gmail.com",
      "summary": "HR 120, BP 145, SpO2 92, Glucose 150",
      "messagePreview": "Test alert: RISKY risk detected. Heart rate elevated, blood pressure high....",
      "messageId": "<6a2a7d40-31be-7fde-bc27-709b73abd89f@gmail.com>",
      "response": "250 2.0.0 OK  1770446069 d2e1a72fcca58-8244168fdf5sm4340768b3a.17 - gsmtp"
    },
    {
      "id": "1770446081417",
      "timestamp": "2026-02-07T06:34:41.417Z",
      "status": "success",
      "riskLevel": "high",
      "recipient": "eswardhavala1@gmail.com",
      "summary": "HR 120, BP 145, SpO2 92, Glucose 150",
      "messagePreview": "Test alert: HIGH risk detected. Heart rate elevated, blood pressure high....",
      "messageId": "<fe1b43de-e7c9-ae41-78a6-56a358e85687@gmail.com>",
      "response": "250 2.0.0 OK  1770446053 d9443c01a7336-2a95e2fad78sm19065995ad.45 - gsmtp"
    }
  ]
}